cli/__init__.py
cli/entry.py
cli/officialaccount.py
cli/tools.py
wxcloud/__init__.py
wxcloud/apis.py
wxcloud/mappings.py
engo_data_cli-0.0.9.dist-info/LICENSE
engo_data_cli-0.0.9.dist-info/METADATA
engo_data_cli-0.0.9.dist-info/WHEEL
engo_data_cli-0.0.9.dist-info/entry_points.txt
engo_data_cli-0.0.9.dist-info/top_level.txt
engo_data_cli-0.0.9.dist-info/RECORD
